dora_transformers/__init__.py
dora_transformers/__main__.py
dora_transformers/main.py
dora_transformers-1.0.0.dist-info/METADATA
dora_transformers-1.0.0.dist-info/WHEEL
dora_transformers-1.0.0.dist-info/entry_points.txt
dora_transformers-1.0.0.dist-info/top_level.txt
dora_transformers-1.0.0.dist-info/RECORD
