Metadata-Version: 2.4
Name: dora-transformers
Version: 1.0.0
Summary: dora-transformer
Author-email: Shashwat Patil <email@email.com>
License: MIT
Requires-Python: >=3.9
Requires-Dist: dora-rs>=0.3.9
Requires-Dist: torch==2.4.0
Requires-Dist: torchvision>=0.19
Requires-Dist: torchaudio>=2.1.0
Requires-Dist: opencv-python>=4.1.1
Requires-Dist: modelscope>=1.18.1
Requires-Dist: accelerate>=1.3.0
Requires-Dist: transformers
Requires-Dist: bitsandbytes>=0.41.1
